<?xml version="1.0" encoding="utf-8"?>
<!DOCTYPE hibernate-mapping PUBLIC "-//Hibernate/Hibernate Mapping DTD 3.0//EN"
"http://www.hibernate.org/dtd/hibernate-mapping-3.0.dtd">
<!-- 
    Mapping file autogenerated by MyEclipse Persistence Tools
-->
<hibernate-mapping>
    <class name="Check" table="check" catalog="javaee2">
        <id name="id" type="java.lang.String">
            <column name="id" length="60" />
            <generator class="assigned" />
        </id>
        <property name="userName" type="java.lang.String">
            <column name="userName" length="60" not-null="true" />
        </property>
        <property name="studyTime" type="java.lang.String">
            <column name="studyTime" length="50" not-null="true" />
        </property>
        <property name="year" type="java.lang.String">
            <column name="year" length="50" not-null="true" />
        </property>
        <property name="className" type="java.lang.String">
            <column name="className" length="50" not-null="true" />
        </property>
        <property name="courseName" type="java.lang.String">
            <column name="courseName" length="50" not-null="true" />
        </property>
        <property name="checkTeacher" type="java.lang.String">
            <column name="checkTeacher" length="50" not-null="true" />
        </property>
        <property name="checkDate" type="java.util.Date">
            <column name="checkDate" length="10" not-null="true" />
        </property>
        <property name="checkState" type="java.lang.Integer">
            <column name="checkState" not-null="true" />
        </property>
    </class>
</hibernate-mapping>
